{
  "resourceType": "Bundle",
  "type": "transaction",
  "entry": [
    {
      "fullUrl": "urn:uuid:c14c3655-f4de-4aa8-8a25-29e6228bed54",
      "resource": {
        "resourceType": "Patient",
        "id": "c14c3655-f4de-4aa8-8a25-29e6228bed54",
        "text": {
          "status": "generated",
          "div": "<div xmlns=\"http://www.w3.org/1999/xhtml\">Generated by <a href=\"https://github.com/synthetichealth/synthea\">Synthea</a>.Version identifier: v2.5.0-281-g7d283ffb\n .   Person seed: -7126425499426240041  Population seed: 1582751636001</div>"
        },
        "extension": [
          {
            "url": "http://hl7.org/fhir/us/core/StructureDefinition/us-core-race",
            "extension": [
              {
                "url": "ombCategory",
                "valueCoding": {
                  "system": "urn:oid:2.16.840.1.113883.6.238",
                  "code": "2106-3",
                  "display": "White"
                }
              },
              {
                "url": "text",
                "valueString": "White"
              }
            ]
          },
          {
            "url": "http://hl7.org/fhir/us/core/StructureDefinition/us-core-ethnicity",
            "extension": [
              {
                "url": "ombCategory",
                "valueCoding": {
                  "system": "urn:oid:2.16.840.1.113883.6.238",
                  "code": "2186-5",
                  "display": "Not Hispanic or Latino"
                }
              },
              {
                "url": "text",
                "valueString": "Not Hispanic or Latino"
              }
            ]
          },
          {
            "url": "http://hl7.org/fhir/StructureDefinition/patient-mothersMaidenName",
            "valueString": "Natividad McClure"
          },
          {
            "url": "http://hl7.org/fhir/us/core/StructureDefinition/us-core-birthsex",
            "valueCode": "M"
          },
          {
            "url": "http://hl7.org/fhir/StructureDefinition/patient-birthPlace",
            "valueAddress": {
              "city": "Sanford",
              "state": "Colorado",
              "country": "US"
            }
          },
          {
            "url": "http://synthetichealth.github.io/synthea/disability-adjusted-life-years",
            "valueDecimal": 0.0
          },
          {
            "url": "http://synthetichealth.github.io/synthea/quality-adjusted-life-years",
            "valueDecimal": 8.0
          }
        ],
        "identifier": [
          {
            "system": "https://github.com/synthetichealth/synthea",
            "value": "c14c3655-f4de-4aa8-8a25-29e6228bed54"
          },
          {
            "type": {
              "coding": [
                {
                  "system": "http://terminology.hl7.org/CodeSystem/v2-0203",
                  "code": "MR",
                  "display": "Medical Record Number"
                }
              ],
              "text": "Medical Record Number"
            },
            "system": "http://hospital.smarthealthit.org",
            "value": "c14c3655-f4de-4aa8-8a25-29e6228bed54"
          },
          {
            "type": {
              "coding": [
                {
                  "system": "http://terminology.hl7.org/CodeSystem/v2-0203",
                  "code": "SS",
                  "display": "Social Security Number"
                }
              ],
              "text": "Social Security Number"
            },
            "system": "http://hl7.org/fhir/sid/us-ssn",
            "value": "999-77-6624"
          },
          {
            "type": {
              "coding": [
                {
                  "system": "http://codi.mitre.org",
                  "code": "KP",
                  "display": "Synthetic Denver List ID"
                }
              ],
              "text": "Synthetic Denver List ID"
            },
            "system": "http://codi.mitre.org",
            "value": "19438660"
          },
          {
            "system": "http://codi.mitre.org/link_id",
            "value": "100580"
          }
        ],
        "name": [
          {
            "use": "official",
            "family": "Noonan",
            "given": [
              "Cameron Dermot"
            ]
          }
        ],
        "telecom": [
          {
            "system": "phone",
            "value": "303-6178759",
            "use": "home"
          }
        ],
        "gender": "male",
        "birthDate": "2011-03-12",
        "address": [
          {
            "extension": [
              {
                "url": "http://hl7.org/fhir/StructureDefinition/geolocation",
                "extension": [
                  {
                    "url": "latitude",
                    "valueDecimal": 39.91542129864923
                  },
                  {
                    "url": "longitude",
                    "valueDecimal": -104.92445380621098
                  }
                ]
              }
            ],
            "line": [
              "4669 E 115th Ct"
            ],
            "city": "Thornton",
            "state": "Colorado",
            "postalCode": "80233-2621",
            "country": "US"
          }
        ],
        "maritalStatus": {
          "coding": [
            {
              "system": "http://terminology.hl7.org/CodeSystem/v3-MaritalStatus",
              "code": "S",
              "display": "Never Married"
            }
          ],
          "text": "Never Married"
        },
        "multipleBirthBoolean": false,
        "contact": [
          {
            "name": {
              "use": "official",
              "family": "Noonan",
              "given": [
                "Anthony Digby"
              ]
            },
            "telecom": [
              {
                "system": "email",
                "value": "tonydreamsmusic@gmail.com",
                "use": "home"
              }
            ]
          }
        ],
        "communication": [
          {
            "language": {
              "coding": [
                {
                  "system": "urn:ietf:bcp:47",
                  "code": "en-US",
                  "display": "English"
                }
              ],
              "text": "English"
            }
          }
        ]
      },
      "request": {
        "method": "POST",
        "url": "Patient"
      }
    },
    {
      "fullUrl": "urn:uuid:703fb4d7-112f-36ca-95e5-e8f838382855",
      "resource": {
        "resourceType": "Organization",
        "id": "703fb4d7-112f-36ca-95e5-e8f838382855",
        "identifier": [
          {
            "system": "https://github.com/synthetichealth/synthea",
            "value": "703fb4d7-112f-36ca-95e5-e8f838382855"
          }
        ],
        "active": true,
        "type": [
          {
            "coding": [
              {
                "system": "http://terminology.hl7.org/CodeSystem/organization-type",
                "code": "prov",
                "display": "Healthcare Provider"
              }
            ],
            "text": "Healthcare Provider"
          }
        ],
        "name": "NORTH SUBURBAN MEDICAL CENTER",
        "telecom": [
          {
            "system": "phone",
            "value": "3034517800"
          }
        ],
        "address": [
          {
            "line": [
              "9191 GRANT ST"
            ],
            "city": "THORNTON",
            "state": "CO",
            "postalCode": "80229",
            "country": "US"
          }
        ]
      },
      "request": {
        "method": "POST",
        "url": "Organization"
      }
    },
    {
      "fullUrl": "urn:uuid:f5f411ad-9a63-38ac-9654-3ae6865fb521",
      "resource": {
        "resourceType": "Practitioner",
        "id": "f5f411ad-9a63-38ac-9654-3ae6865fb521",
        "identifier": [
          {
            "system": "http://hl7.org/fhir/sid/us-npi",
            "value": "280"
          }
        ],
        "active": true,
        "name": [
          {
            "family": "Reinger",
            "given": [
              "Saul"
            ],
            "prefix": [
              "Dr."
            ]
          }
        ],
        "telecom": [
          {
            "system": "email",
            "value": "Saul.Reinger@example.com",
            "use": "work"
          }
        ],
        "address": [
          {
            "line": [
              "9191 GRANT ST"
            ],
            "city": "THORNTON",
            "state": "CO",
            "postalCode": "80229",
            "country": "US"
          }
        ],
        "gender": "male"
      },
      "request": {
        "method": "POST",
        "url": "Practitioner"
      }
    },
    {
      "fullUrl": "urn:uuid:7ddae806-4972-40bf-b5be-acdb7cb56602",
      "resource": {
        "resourceType": "Encounter",
        "id": "7ddae806-4972-40bf-b5be-acdb7cb56602",
        "status": "finished",
        "class": {
          "system": "http://terminology.hl7.org/CodeSystem/v3-ActCode",
          "code": "AMB"
        },
        "type": [
          {
            "coding": [
              {
                "system": "http://snomed.info/sct",
                "code": "185345009",
                "display": "Encounter for symptom"
              }
            ],
            "text": "Encounter for symptom"
          }
        ],
        "subject": {
          "reference": "urn:uuid:c14c3655-f4de-4aa8-8a25-29e6228bed54",
          "display": "Cameron Dermot Noonan"
        },
        "participant": [
          {
            "individual": {
              "reference": "urn:uuid:f5f411ad-9a63-38ac-9654-3ae6865fb521",
              "display": "Dr. Saul Reinger"
            }
          }
        ],
        "period": {
          "start": "2014-06-25T06:00:00-06:00",
          "end": "2014-06-25T06:30:00-06:00"
        },
        "reasonCode": [
          {
            "coding": [
              {
                "system": "http://snomed.info/sct",
                "code": "195662009",
                "display": "Acute viral pharyngitis (disorder)"
              }
            ]
          }
        ],
        "serviceProvider": {
          "reference": "urn:uuid:703fb4d7-112f-36ca-95e5-e8f838382855",
          "display": "NORTH SUBURBAN MEDICAL CENTER"
        }
      },
      "request": {
        "method": "POST",
        "url": "Encounter"
      }
    },
    {
      "fullUrl": "urn:uuid:504e03b9-868a-4d68-a8f3-135e37ac88e7",
      "resource": {
        "resourceType": "Condition",
        "id": "504e03b9-868a-4d68-a8f3-135e37ac88e7",
        "clinicalStatus": {
          "coding": [
            {
              "system": "http://terminology.hl7.org/CodeSystem/condition-clinical",
              "code": "resolved"
            }
          ]
        },
        "verificationStatus": {
          "coding": [
            {
              "system": "http://terminology.hl7.org/CodeSystem/condition-ver-status",
              "code": "confirmed"
            }
          ]
        },
        "code": {
          "coding": [
            {
              "system": "http://snomed.info/sct",
              "code": "195662009",
              "display": "Acute viral pharyngitis (disorder)"
            }
          ],
          "text": "Acute viral pharyngitis (disorder)"
        },
        "subject": {
          "reference": "urn:uuid:c14c3655-f4de-4aa8-8a25-29e6228bed54"
        },
        "encounter": {
          "reference": "urn:uuid:7ddae806-4972-40bf-b5be-acdb7cb56602"
        },
        "onsetDateTime": "2014-06-25T06:00:00-06:00",
        "abatementDateTime": "2014-07-07T06:00:00-06:00",
        "recordedDate": "2014-06-25T06:00:00-06:00"
      },
      "request": {
        "method": "POST",
        "url": "Condition"
      }
    },
    {
      "fullUrl": "urn:uuid:d9d6e58c-1bf9-4212-86d1-3ad653e224b8",
      "resource": {
        "resourceType": "Observation",
        "id": "d9d6e58c-1bf9-4212-86d1-3ad653e224b8",
        "status": "final",
        "category": [
          {
            "coding": [
              {
                "system": "http://terminology.hl7.org/CodeSystem/observation-category",
                "code": "vital-signs",
                "display": "vital-signs"
              }
            ]
          }
        ],
        "code": {
          "coding": [
            {
              "system": "http://loinc.org",
              "code": "8310-5",
              "display": "Body temperature"
            },
            {
              "system": "http://loinc.org",
              "code": "8331-1",
              "display": "Oral temperature"
            }
          ],
          "text": "Body temperature"
        },
        "subject": {
          "reference": "urn:uuid:c14c3655-f4de-4aa8-8a25-29e6228bed54"
        },
        "encounter": {
          "reference": "urn:uuid:7ddae806-4972-40bf-b5be-acdb7cb56602"
        },
        "effectiveDateTime": "2014-06-25T06:00:00-06:00",
        "issued": "2014-06-25T06:00:00.000-06:00",
        "valueQuantity": {
          "value": 37.296,
          "unit": "Cel",
          "system": "http://unitsofmeasure.org",
          "code": "Cel"
        }
      },
      "request": {
        "method": "POST",
        "url": "Observation"
      }
    },
    {
      "fullUrl": "urn:uuid:576d728a-2c43-473b-a7db-670017f0d3ea",
      "resource": {
        "resourceType": "Procedure",
        "id": "576d728a-2c43-473b-a7db-670017f0d3ea",
        "status": "completed",
        "code": {
          "coding": [
            {
              "system": "http://snomed.info/sct",
              "code": "117015009",
              "display": "Throat culture (procedure)"
            }
          ],
          "text": "Throat culture (procedure)"
        },
        "subject": {
          "reference": "urn:uuid:c14c3655-f4de-4aa8-8a25-29e6228bed54"
        },
        "encounter": {
          "reference": "urn:uuid:7ddae806-4972-40bf-b5be-acdb7cb56602"
        },
        "performedPeriod": {
          "start": "2014-06-25T06:00:00-06:00",
          "end": "2014-06-25T06:15:00-06:00"
        },
        "reasonReference": [
          {
            "reference": "urn:uuid:504e03b9-868a-4d68-a8f3-135e37ac88e7",
            "display": "Acute viral pharyngitis (disorder)"
          }
        ]
      },
      "request": {
        "method": "POST",
        "url": "Procedure"
      }
    },
    {
      "fullUrl": "urn:uuid:5a53c208-3670-48b8-ae22-953f10f53158",
      "resource": {
        "resourceType": "Claim",
        "id": "5a53c208-3670-48b8-ae22-953f10f53158",
        "status": "active",
        "type": {
          "coding": [
            {
              "system": "http://terminology.hl7.org/CodeSystem/claim-type",
              "code": "institutional"
            }
          ]
        },
        "use": "claim",
        "patient": {
          "reference": "urn:uuid:c14c3655-f4de-4aa8-8a25-29e6228bed54",
          "display": "Cameron Dermot Noonan"
        },
        "billablePeriod": {
          "start": "2014-06-25T06:00:00-06:00",
          "end": "2014-06-25T06:30:00-06:00"
        },
        "created": "2014-06-25T06:30:00-06:00",
        "provider": {
          "reference": "urn:uuid:703fb4d7-112f-36ca-95e5-e8f838382855",
          "display": "NORTH SUBURBAN MEDICAL CENTER"
        },
        "priority": {
          "coding": [
            {
              "system": "http://terminology.hl7.org/CodeSystem/processpriority",
              "code": "normal"
            }
          ]
        },
        "diagnosis": [
          {
            "sequence": 1,
            "diagnosisReference": {
              "reference": "urn:uuid:504e03b9-868a-4d68-a8f3-135e37ac88e7"
            }
          }
        ],
        "procedure": [
          {
            "sequence": 1,
            "procedureReference": {
              "reference": "urn:uuid:576d728a-2c43-473b-a7db-670017f0d3ea"
            }
          }
        ],
        "insurance": [
          {
            "sequence": 1,
            "focal": true,
            "coverage": {
              "display": "NO_INSURANCE"
            }
          }
        ],
        "item": [
          {
            "sequence": 1,
            "productOrService": {
              "coding": [
                {
                  "system": "http://snomed.info/sct",
                  "code": "185345009",
                  "display": "Encounter for symptom"
                }
              ],
              "text": "Encounter for symptom"
            },
            "encounter": [
              {
                "reference": "urn:uuid:7ddae806-4972-40bf-b5be-acdb7cb56602"
              }
            ]
          },
          {
            "sequence": 2,
            "diagnosisSequence": [
              1
            ],
            "productOrService": {
              "coding": [
                {
                  "system": "http://snomed.info/sct",
                  "code": "195662009",
                  "display": "Acute viral pharyngitis (disorder)"
                }
              ],
              "text": "Acute viral pharyngitis (disorder)"
            }
          },
          {
            "sequence": 3,
            "procedureSequence": [
              1
            ],
            "productOrService": {
              "coding": [
                {
                  "system": "http://snomed.info/sct",
                  "code": "117015009",
                  "display": "Throat culture (procedure)"
                }
              ],
              "text": "Throat culture (procedure)"
            },
            "net": {
              "value": 1753.70,
              "currency": "USD"
            }
          }
        ],
        "total": {
          "value": 115.63,
          "currency": "USD"
        }
      },
      "request": {
        "method": "POST",
        "url": "Claim"
      }
    },
    {
      "fullUrl": "urn:uuid:3a047b4a-0521-4b95-8a86-96182d4e4027",
      "resource": {
        "resourceType": "ExplanationOfBenefit",
        "id": "3a047b4a-0521-4b95-8a86-96182d4e4027",
        "contained": [
          {
            "resourceType": "ServiceRequest",
            "id": "referral",
            "status": "completed",
            "intent": "order",
            "subject": {
              "reference": "urn:uuid:c14c3655-f4de-4aa8-8a25-29e6228bed54"
            },
            "requester": {
              "reference": "urn:uuid:f5f411ad-9a63-38ac-9654-3ae6865fb521"
            },
            "performer": [
              {
                "reference": "urn:uuid:f5f411ad-9a63-38ac-9654-3ae6865fb521"
              }
            ]
          },
          {
            "resourceType": "Coverage",
            "id": "coverage",
            "status": "active",
            "type": {
              "text": "NO_INSURANCE"
            },
            "beneficiary": {
              "reference": "urn:uuid:c14c3655-f4de-4aa8-8a25-29e6228bed54"
            },
            "payor": [
              {
                "display": "NO_INSURANCE"
              }
            ]
          }
        ],
        "identifier": [
          {
            "system": "https://bluebutton.cms.gov/resources/variables/clm_id",
            "value": "5a53c208-3670-48b8-ae22-953f10f53158"
          },
          {
            "system": "https://bluebutton.cms.gov/resources/identifier/claim-group",
            "value": "99999999999"
          }
        ],
        "status": "active",
        "type": {
          "coding": [
            {
              "system": "http://terminology.hl7.org/CodeSystem/claim-type",
              "code": "institutional"
            }
          ]
        },
        "use": "claim",
        "patient": {
          "reference": "urn:uuid:c14c3655-f4de-4aa8-8a25-29e6228bed54"
        },
        "billablePeriod": {
          "start": "2014-06-25T06:30:00-06:00",
          "end": "2015-06-25T06:30:00-06:00"
        },
        "created": "2014-06-25T06:30:00-06:00",
        "insurer": {
          "display": "NO_INSURANCE"
        },
        "provider": {
          "reference": "urn:uuid:f5f411ad-9a63-38ac-9654-3ae6865fb521"
        },
        "referral": {
          "reference": "#referral"
        },
        "claim": {
          "reference": "urn:uuid:5a53c208-3670-48b8-ae22-953f10f53158"
        },
        "outcome": "complete",
        "careTeam": [
          {
            "sequence": 1,
            "provider": {
              "reference": "urn:uuid:f5f411ad-9a63-38ac-9654-3ae6865fb521"
            },
            "role": {
              "coding": [
                {
                  "system": "http://terminology.hl7.org/CodeSystem/claimcareteamrole",
                  "code": "primary",
                  "display": "Primary Care Practitioner"
                }
              ]
            }
          }
        ],
        "diagnosis": [
          {
            "sequence": 1,
            "diagnosisReference": {
              "reference": "urn:uuid:504e03b9-868a-4d68-a8f3-135e37ac88e7"
            },
            "type": [
              {
                "coding": [
                  {
                    "system": "http://terminology.hl7.org/CodeSystem/ex-diagnosistype",
                    "code": "principal"
                  }
                ]
              }
            ]
          }
        ],
        "insurance": [
          {
            "focal": true,
            "coverage": {
              "reference": "#coverage",
              "display": "NO_INSURANCE"
            }
          }
        ],
        "item": [
          {
            "sequence": 1,
            "category": {
              "coding": [
                {
                  "system": "https://bluebutton.cms.gov/resources/variables/line_cms_type_srvc_cd",
                  "code": "1",
                  "display": "Medical care"
                }
              ]
            },
            "productOrService": {
              "coding": [
                {
                  "system": "http://snomed.info/sct",
                  "code": "185345009",
                  "display": "Encounter for symptom"
                }
              ],
              "text": "Encounter for symptom"
            },
            "servicedPeriod": {
              "start": "2014-06-25T06:00:00-06:00",
              "end": "2014-06-25T06:30:00-06:00"
            },
            "locationCodeableConcept": {
              "coding": [
                {
                  "system": "http://terminology.hl7.org/CodeSystem/ex-serviceplace",
                  "code": "21",
                  "display": "Inpatient Hospital"
                }
              ]
            },
            "encounter": [
              {
                "reference": "urn:uuid:7ddae806-4972-40bf-b5be-acdb7cb56602"
              }
            ]
          },
          {
            "sequence": 2,
            "diagnosisSequence": [
              1
            ],
            "category": {
              "coding": [
                {
                  "system": "https://bluebutton.cms.gov/resources/variables/line_cms_type_srvc_cd",
                  "code": "1",
                  "display": "Medical care"
                }
              ]
            },
            "productOrService": {
              "coding": [
                {
                  "system": "http://snomed.info/sct",
                  "code": "195662009",
                  "display": "Acute viral pharyngitis (disorder)"
                }
              ],
              "text": "Acute viral pharyngitis (disorder)"
            },
            "servicedPeriod": {
              "start": "2014-06-25T06:00:00-06:00",
              "end": "2014-06-25T06:30:00-06:00"
            },
            "locationCodeableConcept": {
              "coding": [
                {
                  "system": "http://terminology.hl7.org/CodeSystem/ex-serviceplace",
                  "code": "21",
                  "display": "Inpatient Hospital"
                }
              ]
            }
          },
          {
            "sequence": 3,
            "category": {
              "coding": [
                {
                  "system": "https://bluebutton.cms.gov/resources/variables/line_cms_type_srvc_cd",
                  "code": "1",
                  "display": "Medical care"
                }
              ]
            },
            "productOrService": {
              "coding": [
                {
                  "system": "http://snomed.info/sct",
                  "code": "117015009",
                  "display": "Throat culture (procedure)"
                }
              ],
              "text": "Throat culture (procedure)"
            },
            "servicedPeriod": {
              "start": "2014-06-25T06:00:00-06:00",
              "end": "2014-06-25T06:30:00-06:00"
            },
            "locationCodeableConcept": {
              "coding": [
                {
                  "system": "http://terminology.hl7.org/CodeSystem/ex-serviceplace",
                  "code": "21",
                  "display": "Inpatient Hospital"
                }
              ]
            },
            "net": {
              "value": 1753.70,
              "currency": "USD"
            },
            "adjudication": [
              {
                "category": {
                  "coding": [
                    {
                      "system": "https://bluebutton.cms.gov/resources/codesystem/adjudication",
                      "code": "https://bluebutton.cms.gov/resources/variables/line_coinsrnc_amt",
                      "display": "Line Beneficiary Coinsurance Amount"
                    }
                  ]
                },
                "amount": {
                  "value": 350.74,
                  "currency": "USD"
                }
              },
              {
                "category": {
                  "coding": [
                    {
                      "system": "https://bluebutton.cms.gov/resources/codesystem/adjudication",
                      "code": "https://bluebutton.cms.gov/resources/variables/line_prvdr_pmt_amt",
                      "display": "Line Provider Payment Amount"
                    }
                  ]
                },
                "amount": {
                  "value": 1402.96,
                  "currency": "USD"
                }
              },
              {
                "category": {
                  "coding": [
                    {
                      "system": "https://bluebutton.cms.gov/resources/codesystem/adjudication",
                      "code": "https://bluebutton.cms.gov/resources/variables/line_sbmtd_chrg_amt",
                      "display": "Line Submitted Charge Amount"
                    }
                  ]
                },
                "amount": {
                  "value": 1753.70,
                  "currency": "USD"
                }
              },
              {
                "category": {
                  "coding": [
                    {
                      "system": "https://bluebutton.cms.gov/resources/codesystem/adjudication",
                      "code": "https://bluebutton.cms.gov/resources/variables/line_alowd_chrg_amt",
                      "display": "Line Allowed Charge Amount"
                    }
                  ]
                },
                "amount": {
                  "value": 1753.70,
                  "currency": "USD"
                }
              },
              {
                "category": {
                  "coding": [
                    {
                      "system": "https://bluebutton.cms.gov/resources/codesystem/adjudication",
                      "code": "https://bluebutton.cms.gov/resources/variables/line_bene_ptb_ddctbl_amt",
                      "display": "Line Beneficiary Part B Deductible Amount"
                    }
                  ]
                },
                "amount": {
                  "value": 0,
                  "currency": "USD"
                }
              },
              {
                "category": {
                  "coding": [
                    {
                      "system": "https://bluebutton.cms.gov/resources/codesystem/adjudication",
                      "code": "https://bluebutton.cms.gov/resources/variables/line_prcsg_ind_cd",
                      "display": "Line Processing Indicator Code"
                    }
                  ]
                }
              }
            ]
          }
        ],
        "total": [
          {
            "category": {
              "coding": [
                {
                  "system": "http://terminology.hl7.org/CodeSystem/adjudication",
                  "code": "submitted",
                  "display": "Submitted Amount"
                }
              ],
              "text": "Submitted Amount"
            },
            "amount": {
              "value": 115.63,
              "currency": "USD"
            }
          }
        ],
        "payment": {
          "amount": {
            "value": 1402.96,
            "currency": "USD"
          }
        }
      },
      "request": {
        "method": "POST",
        "url": "ExplanationOfBenefit"
      }
    },
    {
      "fullUrl": "urn:uuid:94faa227-f995-49cf-88c5-825e6551a72c",
      "resource": {
        "resourceType": "Encounter",
        "id": "94faa227-f995-49cf-88c5-825e6551a72c",
        "status": "finished",
        "class": {
          "system": "http://terminology.hl7.org/CodeSystem/v3-ActCode",
          "code": "AMB"
        },
        "type": [
          {
            "coding": [
              {
                "system": "http://snomed.info/sct",
                "code": "185349003",
                "display": "Encounter for check up (procedure)"
              }
            ],
            "text": "Encounter for check up (procedure)"
          }
        ],
        "subject": {
          "reference": "urn:uuid:c14c3655-f4de-4aa8-8a25-29e6228bed54",
          "display": "Cameron Dermot Noonan"
        },
        "participant": [
          {
            "individual": {
              "reference": "urn:uuid:f5f411ad-9a63-38ac-9654-3ae6865fb521",
              "display": "Dr. Saul Reinger"
            }
          }
        ],
        "period": {
          "start": "2014-07-12T06:00:00-06:00",
          "end": "2014-07-12T06:15:00-06:00"
        },
        "serviceProvider": {
          "reference": "urn:uuid:703fb4d7-112f-36ca-95e5-e8f838382855",
          "display": "NORTH SUBURBAN MEDICAL CENTER"
        }
      },
      "request": {
        "method": "POST",
        "url": "Encounter"
      }
    },
    {
      "fullUrl": "urn:uuid:3d81d876-51a1-4d1e-b443-78dc40d9c789",
      "resource": {
        "resourceType": "Observation",
        "id": "3d81d876-51a1-4d1e-b443-78dc40d9c789",
        "status": "final",
        "category": [
          {
            "coding": [
              {
                "system": "http://terminology.hl7.org/CodeSystem/observation-category",
                "code": "vital-signs",
                "display": "vital-signs"
              }
            ]
          }
        ],
        "code": {
          "coding": [
            {
              "system": "http://loinc.org",
              "code": "8302-2",
              "display": "Body Height"
            }
          ],
          "text": "Body Height"
        },
        "subject": {
          "reference": "urn:uuid:c14c3655-f4de-4aa8-8a25-29e6228bed54"
        },
        "encounter": {
          "reference": "urn:uuid:94faa227-f995-49cf-88c5-825e6551a72c"
        },
        "effectiveDateTime": "2014-07-12T06:00:00-06:00",
        "issued": "2014-07-12T06:00:00.000-06:00",
        "valueQuantity": {
          "value": 96.3,
          "unit": "cm",
          "system": "http://unitsofmeasure.org",
          "code": "cm"
        }
      },
      "request": {
        "method": "POST",
        "url": "Observation"
      }
    },
    {
      "fullUrl": "urn:uuid:b426c548-f60f-4022-b4a5-8b06ae7010ef",
      "resource": {
        "resourceType": "Observation",
        "id": "b426c548-f60f-4022-b4a5-8b06ae7010ef",
        "status": "final",
        "category": [
          {
            "coding": [
              {
                "system": "http://terminology.hl7.org/CodeSystem/observation-category",
                "code": "vital-signs",
                "display": "vital-signs"
              }
            ]
          }
        ],
        "code": {
          "coding": [
            {
              "system": "http://loinc.org",
              "code": "72514-3",
              "display": "Pain severity - 0-10 verbal numeric rating [Score] - Reported"
            }
          ],
          "text": "Pain severity - 0-10 verbal numeric rating [Score] - Reported"
        },
        "subject": {
          "reference": "urn:uuid:c14c3655-f4de-4aa8-8a25-29e6228bed54"
        },
        "encounter": {
          "reference": "urn:uuid:94faa227-f995-49cf-88c5-825e6551a72c"
        },
        "effectiveDateTime": "2014-07-12T06:00:00-06:00",
        "issued": "2014-07-12T06:00:00.000-06:00",
        "valueQuantity": {
          "value": 0,
          "unit": "{score}",
          "system": "http://unitsofmeasure.org",
          "code": "{score}"
        }
      },
      "request": {
        "method": "POST",
        "url": "Observation"
      }
    },
    {
      "fullUrl": "urn:uuid:61fc93b2-5ae9-4dd5-9906-c5e193d04a3d",
      "resource": {
        "resourceType": "Observation",
        "id": "61fc93b2-5ae9-4dd5-9906-c5e193d04a3d",
        "status": "final",
        "category": [
          {
            "coding": [
              {
                "system": "http://terminology.hl7.org/CodeSystem/observation-category",
                "code": "vital-signs",
                "display": "vital-signs"
              }
            ]
          }
        ],
        "code": {
          "coding": [
            {
              "system": "http://loinc.org",
              "code": "29463-7",
              "display": "Body Weight"
            }
          ],
          "text": "Body Weight"
        },
        "subject": {
          "reference": "urn:uuid:c14c3655-f4de-4aa8-8a25-29e6228bed54"
        },
        "encounter": {
          "reference": "urn:uuid:94faa227-f995-49cf-88c5-825e6551a72c"
        },
        "effectiveDateTime": "2014-07-12T06:00:00-06:00",
        "issued": "2014-07-12T06:00:00.000-06:00",
        "valueQuantity": {
          "value": 15,
          "unit": "kg",
          "system": "http://unitsofmeasure.org",
          "code": "kg"
        }
      },
      "request": {
        "method": "POST",
        "url": "Observation"
      }
    },
    {
      "fullUrl": "urn:uuid:10f0faf3-1dea-4d78-b496-de03d4a3fa84",
      "resource": {
        "resourceType": "Observation",
        "id": "10f0faf3-1dea-4d78-b496-de03d4a3fa84",
        "status": "final",
        "category": [
          {
            "coding": [
              {
                "system": "http://terminology.hl7.org/CodeSystem/observation-category",
                "code": "vital-signs",
                "display": "vital-signs"
              }
            ]
          }
        ],
        "code": {
          "coding": [
            {
              "system": "http://loinc.org",
              "code": "77606-2",
              "display": "Weight-for-length Per age and sex"
            }
          ],
          "text": "Weight-for-length Per age and sex"
        },
        "subject": {
          "reference": "urn:uuid:c14c3655-f4de-4aa8-8a25-29e6228bed54"
        },
        "encounter": {
          "reference": "urn:uuid:94faa227-f995-49cf-88c5-825e6551a72c"
        },
        "effectiveDateTime": "2014-07-12T06:00:00-06:00",
        "issued": "2014-07-12T06:00:00.000-06:00",
        "valueQuantity": {
          "value": 53.645,
          "unit": "%",
          "system": "http://unitsofmeasure.org",
          "code": "%"
        }
      },
      "request": {
        "method": "POST",
        "url": "Observation"
      }
    },
    {
      "fullUrl": "urn:uuid:36d1050e-a254-451f-b544-1ce059385f12",
      "resource": {
        "resourceType": "Observation",
        "id": "36d1050e-a254-451f-b544-1ce059385f12",
        "status": "final",
        "category": [
          {
            "coding": [
              {
                "system": "http://terminology.hl7.org/CodeSystem/observation-category",
                "code": "vital-signs",
                "display": "vital-signs"
              }
            ]
          }
        ],
        "code": {
          "coding": [
            {
              "system": "http://loinc.org",
              "code": "9843-4",
              "display": "Head Occipital-frontal circumference"
            }
          ],
          "text": "Head Occipital-frontal circumference"
        },
        "subject": {
          "reference": "urn:uuid:c14c3655-f4de-4aa8-8a25-29e6228bed54"
        },
        "encounter": {
          "reference": "urn:uuid:94faa227-f995-49cf-88c5-825e6551a72c"
        },
        "effectiveDateTime": "2014-07-12T06:00:00-06:00",
        "issued": "2014-07-12T06:00:00.000-06:00",
        "valueQuantity": {
          "value": 49.05,
          "unit": "cm",
          "system": "http://unitsofmeasure.org",
          "code": "cm"
        }
      },
      "request": {
        "method": "POST",
        "url": "Observation"
      }
    },
    {
      "fullUrl": "urn:uuid:5674b273-2878-40a4-a349-444b88429b50",
      "resource": {
        "resourceType": "Observation",
        "id": "5674b273-2878-40a4-a349-444b88429b50",
        "status": "final",
        "category": [
          {
            "coding": [
              {
                "system": "http://terminology.hl7.org/CodeSystem/observation-category",
                "code": "vital-signs",
                "display": "vital-signs"
              }
            ]
          }
        ],
        "code": {
          "coding": [
            {
              "system": "http://loinc.org",
              "code": "39156-5",
              "display": "Body Mass Index"
            }
          ],
          "text": "Body Mass Index"
        },
        "subject": {
          "reference": "urn:uuid:c14c3655-f4de-4aa8-8a25-29e6228bed54"
        },
        "encounter": {
          "reference": "urn:uuid:94faa227-f995-49cf-88c5-825e6551a72c"
        },
        "effectiveDateTime": "2014-07-12T06:00:00-06:00",
        "issued": "2014-07-12T06:00:00.000-06:00",
        "valueQuantity": {
          "value": 16.21,
          "unit": "kg/m2",
          "system": "http://unitsofmeasure.org",
          "code": "kg/m2"
        }
      },
      "request": {
        "method": "POST",
        "url": "Observation"
      }
    },
    {
      "fullUrl": "urn:uuid:5a91a4fe-d43a-4130-8ba2-300c157362f5",
      "resource": {
        "resourceType": "Observation",
        "id": "5a91a4fe-d43a-4130-8ba2-300c157362f5",
        "status": "final",
        "category": [
          {
            "coding": [
              {
                "system": "http://terminology.hl7.org/CodeSystem/observation-category",
                "code": "vital-signs",
                "display": "vital-signs"
              }
            ]
          }
        ],
        "code": {
          "coding": [
            {
              "system": "http://loinc.org",
              "code": "59576-9",
              "display": "Body mass index (BMI) [Percentile] Per age and gender"
            }
          ],
          "text": "Body mass index (BMI) [Percentile] Per age and gender"
        },
        "subject": {
          "reference": "urn:uuid:c14c3655-f4de-4aa8-8a25-29e6228bed54"
        },
        "encounter": {
          "reference": "urn:uuid:94faa227-f995-49cf-88c5-825e6551a72c"
        },
        "effectiveDateTime": "2014-07-12T06:00:00-06:00",
        "issued": "2014-07-12T06:00:00.000-06:00",
        "valueQuantity": {
          "value": 61.718,
          "unit": "%",
          "system": "http://unitsofmeasure.org",
          "code": "%"
        }
      },
      "request": {
        "method": "POST",
        "url": "Observation"
      }
    },
    {
      "fullUrl": "urn:uuid:5fac07eb-7f6d-45b9-b050-5b2b99370c0e",
      "resource": {
        "resourceType": "Observation",
        "id": "5fac07eb-7f6d-45b9-b050-5b2b99370c0e",
        "status": "final",
        "category": [
          {
            "coding": [
              {
                "system": "http://terminology.hl7.org/CodeSystem/observation-category",
                "code": "vital-signs",
                "display": "vital-signs"
              }
            ]
          }
        ],
        "code": {
          "coding": [
            {
              "system": "http://loinc.org",
              "code": "85354-9",
              "display": "Blood Pressure"
            }
          ],
          "text": "Blood Pressure"
        },
        "subject": {
          "reference": "urn:uuid:c14c3655-f4de-4aa8-8a25-29e6228bed54"
        },
        "encounter": {
          "reference": "urn:uuid:94faa227-f995-49cf-88c5-825e6551a72c"
        },
        "effectiveDateTime": "2014-07-12T06:00:00-06:00",
        "issued": "2014-07-12T06:00:00.000-06:00",
        "component": [
          {
            "code": {
              "coding": [
                {
                  "system": "http://loinc.org",
                  "code": "8462-4",
                  "display": "Diastolic Blood Pressure"
                }
              ],
              "text": "Diastolic Blood Pressure"
            },
            "valueQuantity": {
              "value": 83,
              "unit": "mm[Hg]",
              "system": "http://unitsofmeasure.org",
              "code": "mm[Hg]"
            }
          },
          {
            "code": {
              "coding": [
                {
                  "system": "http://loinc.org",
                  "code": "8480-6",
                  "display": "Systolic Blood Pressure"
                }
              ],
              "text": "Systolic Blood Pressure"
            },
            "valueQuantity": {
              "value": 1.3E+2,
              "unit": "mm[Hg]",
              "system": "http://unitsofmeasure.org",
              "code": "mm[Hg]"
            }
          }
        ]
      },
      "request": {
        "method": "POST",
        "url": "Observation"
      }
    },
    {
      "fullUrl": "urn:uuid:4740307c-272d-47e9-a89c-6da16520d090",
      "resource": {
        "resourceType": "Observation",
        "id": "4740307c-272d-47e9-a89c-6da16520d090",
        "status": "final",
        "category": [
          {
            "coding": [
              {
                "system": "http://terminology.hl7.org/CodeSystem/observation-category",
                "code": "vital-signs",
                "display": "vital-signs"
              }
            ]
          }
        ],
        "code": {
          "coding": [
            {
              "system": "http://loinc.org",
              "code": "8867-4",
              "display": "Heart rate"
            }
          ],
          "text": "Heart rate"
        },
        "subject": {
          "reference": "urn:uuid:c14c3655-f4de-4aa8-8a25-29e6228bed54"
        },
        "encounter": {
          "reference": "urn:uuid:94faa227-f995-49cf-88c5-825e6551a72c"
        },
        "effectiveDateTime": "2014-07-12T06:00:00-06:00",
        "issued": "2014-07-12T06:00:00.000-06:00",
        "valueQuantity": {
          "value": 1E+2,
          "unit": "/min",
          "system": "http://unitsofmeasure.org",
          "code": "/min"
        }
      },
      "request": {
        "method": "POST",
        "url": "Observation"
      }
    },
    {
      "fullUrl": "urn:uuid:4721436f-db42-475c-bf34-cdfff465c476",
      "resource": {
        "resourceType": "Observation",
        "id": "4721436f-db42-475c-bf34-cdfff465c476",
        "status": "final",
        "category": [
          {
            "coding": [
              {
                "system": "http://terminology.hl7.org/CodeSystem/observation-category",
                "code": "vital-signs",
                "display": "vital-signs"
              }
            ]
          }
        ],
        "code": {
          "coding": [
            {
              "system": "http://loinc.org",
              "code": "9279-1",
              "display": "Respiratory rate"
            }
          ],
          "text": "Respiratory rate"
        },
        "subject": {
          "reference": "urn:uuid:c14c3655-f4de-4aa8-8a25-29e6228bed54"
        },
        "encounter": {
          "reference": "urn:uuid:94faa227-f995-49cf-88c5-825e6551a72c"
        },
        "effectiveDateTime": "2014-07-12T06:00:00-06:00",
        "issued": "2014-07-12T06:00:00.000-06:00",
        "valueQuantity": {
          "value": 14,
          "unit": "/min",
          "system": "http://unitsofmeasure.org",
          "code": "/min"
        }
      },
      "request": {
        "method": "POST",
        "url": "Observation"
      }
    },
    {
      "fullUrl": "urn:uuid:1958340e-b9bf-4bf2-88f9-e5a7272dc056",
      "resource": {
        "resourceType": "Observation",
        "id": "1958340e-b9bf-4bf2-88f9-e5a7272dc056",
        "status": "final",
        "category": [
          {
            "coding": [
              {
                "system": "http://terminology.hl7.org/CodeSystem/observation-category",
                "code": "survey",
                "display": "survey"
              }
            ]
          }
        ],
        "code": {
          "coding": [
            {
              "system": "http://loinc.org",
              "code": "72166-2",
              "display": "Tobacco smoking status NHIS"
            }
          ],
          "text": "Tobacco smoking status NHIS"
        },
        "subject": {
          "reference": "urn:uuid:c14c3655-f4de-4aa8-8a25-29e6228bed54"
        },
        "encounter": {
          "reference": "urn:uuid:94faa227-f995-49cf-88c5-825e6551a72c"
        },
        "effectiveDateTime": "2014-07-12T06:00:00-06:00",
        "issued": "2014-07-12T06:00:00.000-06:00",
        "valueCodeableConcept": {
          "coding": [
            {
              "system": "http://snomed.info/sct",
              "code": "266919005",
              "display": "Never smoker"
            }
          ],
          "text": "Never smoker"
        }
      },
      "request": {
        "method": "POST",
        "url": "Observation"
      }
    },
    {
      "fullUrl": "urn:uuid:e8b6e61b-840a-4f29-948a-5dfcd41aba62",
      "resource": {
        "resourceType": "Procedure",
        "id": "e8b6e61b-840a-4f29-948a-5dfcd41aba62",
        "status": "completed",
        "code": {
          "coding": [
            {
              "system": "http://snomed.info/sct",
              "code": "430193006",
              "display": "Medication Reconciliation (procedure)"
            }
          ],
          "text": "Medication Reconciliation (procedure)"
        },
        "subject": {
          "reference": "urn:uuid:c14c3655-f4de-4aa8-8a25-29e6228bed54"
        },
        "encounter": {
          "reference": "urn:uuid:94faa227-f995-49cf-88c5-825e6551a72c"
        },
        "performedPeriod": {
          "start": "2014-07-12T06:00:00-06:00",
          "end": "2014-07-12T06:15:00-06:00"
        }
      },
      "request": {
        "method": "POST",
        "url": "Procedure"
      }
    },
    {
      "fullUrl": "urn:uuid:66291d81-6539-4160-83db-4e16bc355cae",
      "resource": {
        "resourceType": "Claim",
        "id": "66291d81-6539-4160-83db-4e16bc355cae",
        "status": "active",
        "type": {
          "coding": [
            {
              "system": "http://terminology.hl7.org/CodeSystem/claim-type",
              "code": "institutional"
            }
          ]
        },
        "use": "claim",
        "patient": {
          "reference": "urn:uuid:c14c3655-f4de-4aa8-8a25-29e6228bed54",
          "display": "Cameron Dermot Noonan"
        },
        "billablePeriod": {
          "start": "2014-07-12T06:00:00-06:00",
          "end": "2014-07-12T06:15:00-06:00"
        },
        "created": "2014-07-12T06:15:00-06:00",
        "provider": {
          "reference": "urn:uuid:703fb4d7-112f-36ca-95e5-e8f838382855",
          "display": "NORTH SUBURBAN MEDICAL CENTER"
        },
        "priority": {
          "coding": [
            {
              "system": "http://terminology.hl7.org/CodeSystem/processpriority",
              "code": "normal"
            }
          ]
        },
        "procedure": [
          {
            "sequence": 1,
            "procedureReference": {
              "reference": "urn:uuid:e8b6e61b-840a-4f29-948a-5dfcd41aba62"
            }
          }
        ],
        "insurance": [
          {
            "sequence": 1,
            "focal": true,
            "coverage": {
              "display": "Anthem"
            }
          }
        ],
        "item": [
          {
            "sequence": 1,
            "productOrService": {
              "coding": [
                {
                  "system": "http://snomed.info/sct",
                  "code": "185349003",
                  "display": "Encounter for check up (procedure)"
                }
              ],
              "text": "Encounter for check up (procedure)"
            },
            "encounter": [
              {
                "reference": "urn:uuid:94faa227-f995-49cf-88c5-825e6551a72c"
              }
            ]
          },
          {
            "sequence": 2,
            "procedureSequence": [
              1
            ],
            "productOrService": {
              "coding": [
                {
                  "system": "http://snomed.info/sct",
                  "code": "430193006",
                  "display": "Medication Reconciliation (procedure)"
                }
              ],
              "text": "Medication Reconciliation (procedure)"
            },
            "net": {
              "value": 659.36,
              "currency": "USD"
            }
          }
        ],
        "total": {
          "value": 115.63,
          "currency": "USD"
        }
      },
      "request": {
        "method": "POST",
        "url": "Claim"
      }
    },
    {
      "fullUrl": "urn:uuid:a46322ed-b866-44b8-b698-641f6eab2345",
      "resource": {
        "resourceType": "ExplanationOfBenefit",
        "id": "a46322ed-b866-44b8-b698-641f6eab2345",
        "contained": [
          {
            "resourceType": "ServiceRequest",
            "id": "referral",
            "status": "completed",
            "intent": "order",
            "subject": {
              "reference": "urn:uuid:c14c3655-f4de-4aa8-8a25-29e6228bed54"
            },
            "requester": {
              "reference": "urn:uuid:f5f411ad-9a63-38ac-9654-3ae6865fb521"
            },
            "performer": [
              {
                "reference": "urn:uuid:f5f411ad-9a63-38ac-9654-3ae6865fb521"
              }
            ]
          },
          {
            "resourceType": "Coverage",
            "id": "coverage",
            "status": "active",
            "type": {
              "text": "Anthem"
            },
            "beneficiary": {
              "reference": "urn:uuid:c14c3655-f4de-4aa8-8a25-29e6228bed54"
            },
            "payor": [
              {
                "display": "Anthem"
              }
            ]
          }
        ],
        "identifier": [
          {
            "system": "https://bluebutton.cms.gov/resources/variables/clm_id",
            "value": "66291d81-6539-4160-83db-4e16bc355cae"
          },
          {
            "system": "https://bluebutton.cms.gov/resources/identifier/claim-group",
            "value": "99999999999"
          }
        ],
        "status": "active",
        "type": {
          "coding": [
            {
              "system": "http://terminology.hl7.org/CodeSystem/claim-type",
              "code": "institutional"
            }
          ]
        },
        "use": "claim",
        "patient": {
          "reference": "urn:uuid:c14c3655-f4de-4aa8-8a25-29e6228bed54"
        },
        "billablePeriod": {
          "start": "2014-07-12T06:15:00-06:00",
          "end": "2015-07-12T06:15:00-06:00"
        },
        "created": "2014-07-12T06:15:00-06:00",
        "insurer": {
          "display": "Anthem"
        },
        "provider": {
          "reference": "urn:uuid:f5f411ad-9a63-38ac-9654-3ae6865fb521"
        },
        "referral": {
          "reference": "#referral"
        },
        "claim": {
          "reference": "urn:uuid:66291d81-6539-4160-83db-4e16bc355cae"
        },
        "outcome": "complete",
        "careTeam": [
          {
            "sequence": 1,
            "provider": {
              "reference": "urn:uuid:f5f411ad-9a63-38ac-9654-3ae6865fb521"
            },
            "role": {
              "coding": [
                {
                  "system": "http://terminology.hl7.org/CodeSystem/claimcareteamrole",
                  "code": "primary",
                  "display": "Primary Care Practitioner"
                }
              ]
            }
          }
        ],
        "insurance": [
          {
            "focal": true,
            "coverage": {
              "reference": "#coverage",
              "display": "Anthem"
            }
          }
        ],
        "item": [
          {
            "sequence": 1,
            "category": {
              "coding": [
                {
                  "system": "https://bluebutton.cms.gov/resources/variables/line_cms_type_srvc_cd",
                  "code": "1",
                  "display": "Medical care"
                }
              ]
            },
            "productOrService": {
              "coding": [
                {
                  "system": "http://snomed.info/sct",
                  "code": "185349003",
                  "display": "Encounter for check up (procedure)"
                }
              ],
              "text": "Encounter for check up (procedure)"
            },
            "servicedPeriod": {
              "start": "2014-07-12T06:00:00-06:00",
              "end": "2014-07-12T06:15:00-06:00"
            },
            "locationCodeableConcept": {
              "coding": [
                {
                  "system": "http://terminology.hl7.org/CodeSystem/ex-serviceplace",
                  "code": "21",
                  "display": "Inpatient Hospital"
                }
              ]
            },
            "encounter": [
              {
                "reference": "urn:uuid:94faa227-f995-49cf-88c5-825e6551a72c"
              }
            ]
          },
          {
            "sequence": 2,
            "category": {
              "coding": [
                {
                  "system": "https://bluebutton.cms.gov/resources/variables/line_cms_type_srvc_cd",
                  "code": "1",
                  "display": "Medical care"
                }
              ]
            },
            "productOrService": {
              "coding": [
                {
                  "system": "http://snomed.info/sct",
                  "code": "430193006",
                  "display": "Medication Reconciliation (procedure)"
                }
              ],
              "text": "Medication Reconciliation (procedure)"
            },
            "servicedPeriod": {
              "start": "2014-07-12T06:00:00-06:00",
              "end": "2014-07-12T06:15:00-06:00"
            },
            "locationCodeableConcept": {
              "coding": [
                {
                  "system": "http://terminology.hl7.org/CodeSystem/ex-serviceplace",
                  "code": "21",
                  "display": "Inpatient Hospital"
                }
              ]
            },
            "net": {
              "value": 659.36,
              "currency": "USD"
            },
            "adjudication": [
              {
                "category": {
                  "coding": [
                    {
                      "system": "https://bluebutton.cms.gov/resources/codesystem/adjudication",
                      "code": "https://bluebutton.cms.gov/resources/variables/line_coinsrnc_amt",
                      "display": "Line Beneficiary Coinsurance Amount"
                    }
                  ]
                },
                "amount": {
                  "value": 131.872,
                  "currency": "USD"
                }
              },
              {
                "category": {
                  "coding": [
                    {
                      "system": "https://bluebutton.cms.gov/resources/codesystem/adjudication",
                      "code": "https://bluebutton.cms.gov/resources/variables/line_prvdr_pmt_amt",
                      "display": "Line Provider Payment Amount"
                    }
                  ]
                },
                "amount": {
                  "value": 527.488,
                  "currency": "USD"
                }
              },
              {
                "category": {
                  "coding": [
                    {
                      "system": "https://bluebutton.cms.gov/resources/codesystem/adjudication",
                      "code": "https://bluebutton.cms.gov/resources/variables/line_sbmtd_chrg_amt",
                      "display": "Line Submitted Charge Amount"
                    }
                  ]
                },
                "amount": {
                  "value": 659.36,
                  "currency": "USD"
                }
              },
              {
                "category": {
                  "coding": [
                    {
                      "system": "https://bluebutton.cms.gov/resources/codesystem/adjudication",
                      "code": "https://bluebutton.cms.gov/resources/variables/line_alowd_chrg_amt",
                      "display": "Line Allowed Charge Amount"
                    }
                  ]
                },
                "amount": {
                  "value": 659.36,
                  "currency": "USD"
                }
              },
              {
                "category": {
                  "coding": [
                    {
                      "system": "https://bluebutton.cms.gov/resources/codesystem/adjudication",
                      "code": "https://bluebutton.cms.gov/resources/variables/line_bene_ptb_ddctbl_amt",
                      "display": "Line Beneficiary Part B Deductible Amount"
                    }
                  ]
                },
                "amount": {
                  "value": 0,
                  "currency": "USD"
                }
              },
              {
                "category": {
                  "coding": [
                    {
                      "system": "https://bluebutton.cms.gov/resources/codesystem/adjudication",
                      "code": "https://bluebutton.cms.gov/resources/variables/line_prcsg_ind_cd",
                      "display": "Line Processing Indicator Code"
                    }
                  ]
                }
              }
            ]
          }
        ],
        "total": [
          {
            "category": {
              "coding": [
                {
                  "system": "http://terminology.hl7.org/CodeSystem/adjudication",
                  "code": "submitted",
                  "display": "Submitted Amount"
                }
              ],
              "text": "Submitted Amount"
            },
            "amount": {
              "value": 115.63,
              "currency": "USD"
            }
          }
        ],
        "payment": {
          "amount": {
            "value": 527.488,
            "currency": "USD"
          }
        }
      },
      "request": {
        "method": "POST",
        "url": "ExplanationOfBenefit"
      }
    },
    {
      "fullUrl": "urn:uuid:e4429cea-e84b-43c2-a3b2-95c2f265dcef",
      "resource": {
        "resourceType": "Encounter",
        "id": "e4429cea-e84b-43c2-a3b2-95c2f265dcef",
        "status": "finished",
        "class": {
          "system": "http://terminology.hl7.org/CodeSystem/v3-ActCode",
          "code": "EMER"
        },
        "type": [
          {
            "coding": [
              {
                "system": "http://snomed.info/sct",
                "code": "50849002",
                "display": "Emergency room admission (procedure)"
              }
            ],
            "text": "Emergency room admission (procedure)"
          }
        ],
        "subject": {
          "reference": "urn:uuid:c14c3655-f4de-4aa8-8a25-29e6228bed54",
          "display": "Cameron Dermot Noonan"
        },
        "participant": [
          {
            "individual": {
              "reference": "urn:uuid:f5f411ad-9a63-38ac-9654-3ae6865fb521",
              "display": "Dr. Saul Reinger"
            }
          }
        ],
        "period": {
          "start": "2019-09-26T06:00:00-06:00",
          "end": "2019-09-26T07:00:00-06:00"
        },
        "serviceProvider": {
          "reference": "urn:uuid:703fb4d7-112f-36ca-95e5-e8f838382855",
          "display": "NORTH SUBURBAN MEDICAL CENTER"
        }
      },
      "request": {
        "method": "POST",
        "url": "Encounter"
      }
    },
    {
      "fullUrl": "urn:uuid:29b0358a-8ee1-4cb2-a378-ca0fd5c05aa7",
      "resource": {
        "resourceType": "Condition",
        "id": "29b0358a-8ee1-4cb2-a378-ca0fd5c05aa7",
        "clinicalStatus": {
          "coding": [
            {
              "system": "http://terminology.hl7.org/CodeSystem/condition-clinical",
              "code": "resolved"
            }
          ]
        },
        "verificationStatus": {
          "coding": [
            {
              "system": "http://terminology.hl7.org/CodeSystem/condition-ver-status",
              "code": "confirmed"
            }
          ]
        },
        "code": {
          "coding": [
            {
              "system": "http://snomed.info/sct",
              "code": "44465007",
              "display": "Sprain of ankle"
            }
          ],
          "text": "Sprain of ankle"
        },
        "subject": {
          "reference": "urn:uuid:c14c3655-f4de-4aa8-8a25-29e6228bed54"
        },
        "encounter": {
          "reference": "urn:uuid:e4429cea-e84b-43c2-a3b2-95c2f265dcef"
        },
        "onsetDateTime": "2019-09-26T06:00:00-06:00",
        "abatementDateTime": "2019-10-17T06:00:00-06:00",
        "recordedDate": "2019-09-26T06:00:00-06:00"
      },
      "request": {
        "method": "POST",
        "url": "Condition"
      }
    },
    {
      "fullUrl": "urn:uuid:4d670504-203d-4af8-9e99-5ad9ce5c5073",
      "resource": {
        "resourceType": "MedicationRequest",
        "id": "4d670504-203d-4af8-9e99-5ad9ce5c5073",
        "status": "stopped",
        "intent": "order",
        "medicationCodeableConcept": {
          "coding": [
            {
              "system": "http://www.nlm.nih.gov/research/umls/rxnorm",
              "code": "198405",
              "display": "Ibuprofen 100 MG Oral Tablet"
            }
          ],
          "text": "Ibuprofen 100 MG Oral Tablet"
        },
        "subject": {
          "reference": "urn:uuid:c14c3655-f4de-4aa8-8a25-29e6228bed54"
        },
        "encounter": {
          "reference": "urn:uuid:e4429cea-e84b-43c2-a3b2-95c2f265dcef"
        },
        "authoredOn": "2019-09-26T06:00:00-06:00",
        "requester": {
          "reference": "urn:uuid:f5f411ad-9a63-38ac-9654-3ae6865fb521",
          "display": "Dr. Saul Reinger"
        },
        "dosageInstruction": [
          {
            "sequence": 1,
            "asNeededBoolean": true
          }
        ]
      },
      "request": {
        "method": "POST",
        "url": "MedicationRequest"
      }
    },
    {
      "fullUrl": "urn:uuid:2dd6d6ed-e921-431d-b98f-96bef682252b",
      "resource": {
        "resourceType": "Claim",
        "id": "2dd6d6ed-e921-431d-b98f-96bef682252b",
        "status": "active",
        "type": {
          "coding": [
            {
              "system": "http://terminology.hl7.org/CodeSystem/claim-type",
              "code": "pharmacy"
            }
          ]
        },
        "use": "claim",
        "patient": {
          "reference": "urn:uuid:c14c3655-f4de-4aa8-8a25-29e6228bed54"
        },
        "billablePeriod": {
          "start": "2019-09-26T06:00:00-06:00",
          "end": "2019-09-26T07:00:00-06:00"
        },
        "created": "2019-09-26T07:00:00-06:00",
        "provider": {
          "reference": "urn:uuid:703fb4d7-112f-36ca-95e5-e8f838382855",
          "display": "NORTH SUBURBAN MEDICAL CENTER"
        },
        "priority": {
          "coding": [
            {
              "system": "http://terminology.hl7.org/CodeSystem/processpriority",
              "code": "normal"
            }
          ]
        },
        "prescription": {
          "reference": "urn:uuid:4d670504-203d-4af8-9e99-5ad9ce5c5073"
        },
        "insurance": [
          {
            "sequence": 1,
            "focal": true,
            "coverage": {
              "display": "Anthem"
            }
          }
        ],
        "item": [
          {
            "sequence": 1,
            "productOrService": {
              "coding": [
                {
                  "system": "http://snomed.info/sct",
                  "code": "50849002",
                  "display": "Emergency room admission (procedure)"
                }
              ],
              "text": "Emergency room admission (procedure)"
            },
            "encounter": [
              {
                "reference": "urn:uuid:e4429cea-e84b-43c2-a3b2-95c2f265dcef"
              }
            ]
          }
        ],
        "total": {
          "value": 27.49,
          "currency": "USD"
        }
      },
      "request": {
        "method": "POST",
        "url": "Claim"
      }
    },
    {
      "fullUrl": "urn:uuid:249f6490-d25d-4921-a502-dc20ab18dc3a",
      "resource": {
        "resourceType": "CareTeam",
        "id": "249f6490-d25d-4921-a502-dc20ab18dc3a",
        "status": "inactive",
        "subject": {
          "reference": "urn:uuid:c14c3655-f4de-4aa8-8a25-29e6228bed54"
        },
        "encounter": {
          "reference": "urn:uuid:e4429cea-e84b-43c2-a3b2-95c2f265dcef"
        },
        "period": {
          "start": "2019-09-26T06:00:00-06:00",
          "end": "2019-10-17T06:00:00-06:00"
        },
        "participant": [
          {
            "role": [
              {
                "coding": [
                  {
                    "system": "http://snomed.info/sct",
                    "code": "116153009",
                    "display": "Patient"
                  }
                ],
                "text": "Patient"
              }
            ],
            "member": {
              "reference": "urn:uuid:c14c3655-f4de-4aa8-8a25-29e6228bed54",
              "display": "Cameron Dermot Noonan"
            }
          },
          {
            "role": [
              {
                "coding": [
                  {
                    "system": "http://snomed.info/sct",
                    "code": "303118004",
                    "display": "Person in the healthcare environment (person)"
                  }
                ],
                "text": "Person in the healthcare environment (person)"
              }
            ],
            "member": {
              "reference": "urn:uuid:f5f411ad-9a63-38ac-9654-3ae6865fb521",
              "display": "Dr. Saul Reinger"
            }
          },
          {
            "role": [
              {
                "coding": [
                  {
                    "system": "http://snomed.info/sct",
                    "code": "303118004",
                    "display": "Healthcare related organization (qualifier value)"
                  }
                ],
                "text": "Healthcare related organization (qualifier value)"
              }
            ],
            "member": {
              "reference": "urn:uuid:703fb4d7-112f-36ca-95e5-e8f838382855",
              "display": "NORTH SUBURBAN MEDICAL CENTER"
            }
          }
        ],
        "reasonCode": [
          {
            "coding": [
              {
                "system": "http://snomed.info/sct",
                "code": "44465007",
                "display": "Sprain of ankle"
              }
            ],
            "text": "Sprain of ankle"
          }
        ],
        "managingOrganization": [
          {
            "reference": "urn:uuid:703fb4d7-112f-36ca-95e5-e8f838382855",
            "display": "NORTH SUBURBAN MEDICAL CENTER"
          }
        ]
      },
      "request": {
        "method": "POST",
        "url": "CareTeam"
      }
    },
    {
      "fullUrl": "urn:uuid:c2bc6c44-c05d-4169-8181-05f66884bf4d",
      "resource": {
        "resourceType": "CarePlan",
        "id": "c2bc6c44-c05d-4169-8181-05f66884bf4d",
        "text": {
          "status": "generated",
          "div": "<div xmlns=\"http://www.w3.org/1999/xhtml\">Care Plan for Physical therapy procedure.<br/>Activities: <ul><li>Physical therapy procedure</li><li>Physical therapy procedure</li></ul><br/>Care plan is meant to treat Sprain of ankle.</div>"
        },
        "status": "completed",
        "intent": "order",
        "category": [
          {
            "coding": [
              {
                "system": "http://snomed.info/sct",
                "code": "91251008",
                "display": "Physical therapy procedure"
              }
            ],
            "text": "Physical therapy procedure"
          }
        ],
        "subject": {
          "reference": "urn:uuid:c14c3655-f4de-4aa8-8a25-29e6228bed54"
        },
        "encounter": {
          "reference": "urn:uuid:e4429cea-e84b-43c2-a3b2-95c2f265dcef"
        },
        "period": {
          "start": "2019-09-26T06:00:00-06:00",
          "end": "2019-10-17T06:00:00-06:00"
        },
        "careTeam": [
          {
            "reference": "urn:uuid:249f6490-d25d-4921-a502-dc20ab18dc3a"
          }
        ],
        "addresses": [
          {
            "reference": "urn:uuid:29b0358a-8ee1-4cb2-a378-ca0fd5c05aa7"
          }
        ],
        "activity": [
          {
            "detail": {
              "code": {
                "coding": [
                  {
                    "system": "http://snomed.info/sct",
                    "code": "229586001",
                    "display": "Rest, ice, compression and elevation treatment programme"
                  }
                ],
                "text": "Rest, ice, compression and elevation treatment programme"
              },
              "status": "completed",
              "location": {
                "display": "NORTH SUBURBAN MEDICAL CENTER"
              }
            }
          },
          {
            "detail": {
              "code": {
                "coding": [
                  {
                    "system": "http://snomed.info/sct",
                    "code": "229070002",
                    "display": "Stretching exercises"
                  }
                ],
                "text": "Stretching exercises"
              },
              "status": "completed",
              "location": {
                "display": "NORTH SUBURBAN MEDICAL CENTER"
              }
            }
          }
        ]
      },
      "request": {
        "method": "POST",
        "url": "CarePlan"
      }
    },
    {
      "fullUrl": "urn:uuid:6b1659f6-53c3-488e-bc3b-11a3f4906a8a",
      "resource": {
        "resourceType": "Claim",
        "id": "6b1659f6-53c3-488e-bc3b-11a3f4906a8a",
        "status": "active",
        "type": {
          "coding": [
            {
              "system": "http://terminology.hl7.org/CodeSystem/claim-type",
              "code": "institutional"
            }
          ]
        },
        "use": "claim",
        "patient": {
          "reference": "urn:uuid:c14c3655-f4de-4aa8-8a25-29e6228bed54",
          "display": "Cameron Dermot Noonan"
        },
        "billablePeriod": {
          "start": "2019-09-26T06:00:00-06:00",
          "end": "2019-09-26T07:00:00-06:00"
        },
        "created": "2019-09-26T07:00:00-06:00",
        "provider": {
          "reference": "urn:uuid:703fb4d7-112f-36ca-95e5-e8f838382855",
          "display": "NORTH SUBURBAN MEDICAL CENTER"
        },
        "priority": {
          "coding": [
            {
              "system": "http://terminology.hl7.org/CodeSystem/processpriority",
              "code": "normal"
            }
          ]
        },
        "diagnosis": [
          {
            "sequence": 1,
            "diagnosisReference": {
              "reference": "urn:uuid:29b0358a-8ee1-4cb2-a378-ca0fd5c05aa7"
            }
          }
        ],
        "insurance": [
          {
            "sequence": 1,
            "focal": true,
            "coverage": {
              "display": "NO_INSURANCE"
            }
          }
        ],
        "item": [
          {
            "sequence": 1,
            "productOrService": {
              "coding": [
                {
                  "system": "http://snomed.info/sct",
                  "code": "50849002",
                  "display": "Emergency room admission (procedure)"
                }
              ],
              "text": "Emergency room admission (procedure)"
            },
            "encounter": [
              {
                "reference": "urn:uuid:e4429cea-e84b-43c2-a3b2-95c2f265dcef"
              }
            ]
          },
          {
            "sequence": 2,
            "diagnosisSequence": [
              1
            ],
            "productOrService": {
              "coding": [
                {
                  "system": "http://snomed.info/sct",
                  "code": "44465007",
                  "display": "Sprain of ankle"
                }
              ],
              "text": "Sprain of ankle"
            }
          }
        ],
        "total": {
          "value": 115.63,
          "currency": "USD"
        }
      },
      "request": {
        "method": "POST",
        "url": "Claim"
      }
    },
    {
      "fullUrl": "urn:uuid:d4d3f45d-e821-4c41-8834-79cdde141368",
      "resource": {
        "resourceType": "ExplanationOfBenefit",
        "id": "d4d3f45d-e821-4c41-8834-79cdde141368",
        "contained": [
          {
            "resourceType": "ServiceRequest",
            "id": "referral",
            "status": "completed",
            "intent": "order",
            "subject": {
              "reference": "urn:uuid:c14c3655-f4de-4aa8-8a25-29e6228bed54"
            },
            "requester": {
              "reference": "urn:uuid:f5f411ad-9a63-38ac-9654-3ae6865fb521"
            },
            "performer": [
              {
                "reference": "urn:uuid:f5f411ad-9a63-38ac-9654-3ae6865fb521"
              }
            ]
          },
          {
            "resourceType": "Coverage",
            "id": "coverage",
            "status": "active",
            "type": {
              "text": "NO_INSURANCE"
            },
            "beneficiary": {
              "reference": "urn:uuid:c14c3655-f4de-4aa8-8a25-29e6228bed54"
            },
            "payor": [
              {
                "display": "NO_INSURANCE"
              }
            ]
          }
        ],
        "identifier": [
          {
            "system": "https://bluebutton.cms.gov/resources/variables/clm_id",
            "value": "6b1659f6-53c3-488e-bc3b-11a3f4906a8a"
          },
          {
            "system": "https://bluebutton.cms.gov/resources/identifier/claim-group",
            "value": "99999999999"
          }
        ],
        "status": "active",
        "type": {
          "coding": [
            {
              "system": "http://terminology.hl7.org/CodeSystem/claim-type",
              "code": "institutional"
            }
          ]
        },
        "use": "claim",
        "patient": {
          "reference": "urn:uuid:c14c3655-f4de-4aa8-8a25-29e6228bed54"
        },
        "billablePeriod": {
          "start": "2019-09-26T07:00:00-06:00",
          "end": "2020-09-26T07:00:00-06:00"
        },
        "created": "2019-09-26T07:00:00-06:00",
        "insurer": {
          "display": "NO_INSURANCE"
        },
        "provider": {
          "reference": "urn:uuid:f5f411ad-9a63-38ac-9654-3ae6865fb521"
        },
        "referral": {
          "reference": "#referral"
        },
        "claim": {
          "reference": "urn:uuid:6b1659f6-53c3-488e-bc3b-11a3f4906a8a"
        },
        "outcome": "complete",
        "careTeam": [
          {
            "sequence": 1,
            "provider": {
              "reference": "urn:uuid:f5f411ad-9a63-38ac-9654-3ae6865fb521"
            },
            "role": {
              "coding": [
                {
                  "system": "http://terminology.hl7.org/CodeSystem/claimcareteamrole",
                  "code": "primary",
                  "display": "Primary Care Practitioner"
                }
              ]
            }
          }
        ],
        "diagnosis": [
          {
            "sequence": 1,
            "diagnosisReference": {
              "reference": "urn:uuid:29b0358a-8ee1-4cb2-a378-ca0fd5c05aa7"
            },
            "type": [
              {
                "coding": [
                  {
                    "system": "http://terminology.hl7.org/CodeSystem/ex-diagnosistype",
                    "code": "principal"
                  }
                ]
              }
            ]
          }
        ],
        "insurance": [
          {
            "focal": true,
            "coverage": {
              "reference": "#coverage",
              "display": "NO_INSURANCE"
            }
          }
        ],
        "item": [
          {
            "sequence": 1,
            "category": {
              "coding": [
                {
                  "system": "https://bluebutton.cms.gov/resources/variables/line_cms_type_srvc_cd",
                  "code": "1",
                  "display": "Medical care"
                }
              ]
            },
            "productOrService": {
              "coding": [
                {
                  "system": "http://snomed.info/sct",
                  "code": "50849002",
                  "display": "Emergency room admission (procedure)"
                }
              ],
              "text": "Emergency room admission (procedure)"
            },
            "servicedPeriod": {
              "start": "2019-09-26T06:00:00-06:00",
              "end": "2019-09-26T07:00:00-06:00"
            },
            "locationCodeableConcept": {
              "coding": [
                {
                  "system": "http://terminology.hl7.org/CodeSystem/ex-serviceplace",
                  "code": "20",
                  "display": "Urgent Care Facility"
                }
              ]
            },
            "encounter": [
              {
                "reference": "urn:uuid:e4429cea-e84b-43c2-a3b2-95c2f265dcef"
              }
            ]
          },
          {
            "sequence": 2,
            "diagnosisSequence": [
              1
            ],
            "category": {
              "coding": [
                {
                  "system": "https://bluebutton.cms.gov/resources/variables/line_cms_type_srvc_cd",
                  "code": "1",
                  "display": "Medical care"
                }
              ]
            },
            "productOrService": {
              "coding": [
                {
                  "system": "http://snomed.info/sct",
                  "code": "44465007",
                  "display": "Sprain of ankle"
                }
              ],
              "text": "Sprain of ankle"
            },
            "servicedPeriod": {
              "start": "2019-09-26T06:00:00-06:00",
              "end": "2019-09-26T07:00:00-06:00"
            },
            "locationCodeableConcept": {
              "coding": [
                {
                  "system": "http://terminology.hl7.org/CodeSystem/ex-serviceplace",
                  "code": "20",
                  "display": "Urgent Care Facility"
                }
              ]
            }
          }
        ],
        "total": [
          {
            "category": {
              "coding": [
                {
                  "system": "http://terminology.hl7.org/CodeSystem/adjudication",
                  "code": "submitted",
                  "display": "Submitted Amount"
                }
              ],
              "text": "Submitted Amount"
            },
            "amount": {
              "value": 115.63,
              "currency": "USD"
            }
          }
        ],
        "payment": {
          "amount": {
            "value": 0.0,
            "currency": "USD"
          }
        }
      },
      "request": {
        "method": "POST",
        "url": "ExplanationOfBenefit"
      }
    }
  ]
}
